paf/assertion.py
paf/common.py
paf/component.py
paf/config.py
paf/control.py
paf/dom.py
paf/javascript.py
paf/listener.py
paf/locator.py
paf/manager.py
paf/page.py
paf/request.py
paf/types.py
paf/uielement.py
paf/xpath.py
python_automation_framework-0.2.4.dist-info/licenses/LICENSE.txt
python_automation_framework-0.2.4.dist-info/METADATA
python_automation_framework-0.2.4.dist-info/WHEEL
python_automation_framework-0.2.4.dist-info/top_level.txt
python_automation_framework-0.2.4.dist-info/RECORD
