Metadata-Version: 2.4
Name: python-automation-framework
Version: 0.2.4
Summary: Automation framework for the WebDriver API
Home-page: https://github.com/mreiche/python-automation-framework
Author: Mike Reiche
Requires-Python: >=3.13
License-File: LICENSE.txt
Requires-Dist: inject>=4.3.1
Requires-Dist: selenium>=4.23.1
Requires-Dist: is-empty>=1.0.1
Dynamic: author
Dynamic: description
Dynamic: description-content-type
Dynamic: home-page
Dynamic: license-file
Dynamic: requires-dist
Dynamic: requires-python
Dynamic: summary
